MANIFEST.in
README.md
requirements.txt
setup.cfg
setup.py
s3browser/__init__.py
s3browser/client.py
s3browser/helpers.py
s3browser/main.py
s3browser.egg-info/PKG-INFO
s3browser.egg-info/SOURCES.txt
s3browser.egg-info/dependency_links.txt
s3browser.egg-info/entry_points.txt
s3browser.egg-info/not-zip-safe
s3browser.egg-info/requires.txt
s3browser.egg-info/top_level.txt
s3browser/util/__init__.py
s3browser/util/decorators.py
s3browser/util/list.py
s3browser/util/parsers.py
s3browser/util/path.py
s3browser/util/s3.py
s3browser/util/tree.py