Metadata-Version: 1.1
Name: s3browser
Version: 0.0.1
Summary: s3browser
Home-page: https://github.com/andrewgross/s3browser
Author: Andrew Gross
Author-email: andrew.w.gross@gmail.com
License: UNKNOWN
Platform: UNKNOWN
Classifier: Programming Language :: Python
